polars_validate-0.2.0.dist-info/METADATA
polars_validate-0.2.0.dist-info/WHEEL
polars_validate-0.2.0.dist-info/entry_points.txt
polars_validate-0.2.0.dist-info/licenses/LICENSE
polars_validate/__init__.py
polars_validate/base.py
polars_validate/constants.py
polars_validate/frame.py
polars_validate/schema.py
polars_validate/series.py
polars_validate-0.2.0.dist-info/RECORD
