Metadata-Version: 2.4
Name: polars-validate
Version: 0.2.0
Summary: Validate Polars DataFrames using type hints
Keywords: polars,validation,schema,series,dataframe,data,typing
Author: Christopher McDonald
License-File: LICENSE
Classifier: Development Status :: 4 - Beta
Classifier: Operating System :: OS Independent
Classifier: Intended Audience :: Developers
Classifier: Intended Audience :: Science/Research
Classifier: Topic :: Software Development
Classifier: Topic :: Software Development :: Libraries
Classifier: Topic :: Software Development :: Libraries :: Python Modules
Classifier: Topic :: Scientific/Engineering
Classifier: Programming Language :: Python
Classifier: Programming Language :: Python :: 3
Classifier: Programming Language :: Python :: 3 :: Only
Classifier: Programming Language :: Python :: 3.9
Classifier: Programming Language :: Python :: 3.10
Classifier: Programming Language :: Python :: 3.11
Classifier: License :: OSI Approved :: MIT License
Project-URL: Repository, http://github.com/chris-mcdo/polars-validate
Requires-Python: >=3.9
Requires-Dist: polars>=1
